{
  "kind": "collectionType",
  "collectionName": "pages",
  "info": {
    "name": "page",
    "description": ""
  },
  "options": {
    "increments": true,
    "timestamps": true,
    "draftAndPublish": true
  },
  "pluginOptions": {},
  "attributes": {
    "title": {
      "type": "string"
    },
    "slug": {
      "type": "uid",
      "targetField": "title"
    },
    "components": {
      "type": "dynamiczone",
      "components": [
        "ui.jumbotron",
        "ui.jumbotron-with-victims"
      ]
    }
  }
}
